qahirah.py
Qahirah-1.1.dist-info/COPYING
Qahirah-1.1.dist-info/METADATA
Qahirah-1.1.dist-info/WHEEL
Qahirah-1.1.dist-info/top_level.txt
Qahirah-1.1.dist-info/RECORD
